<?xml version="1.0" encoding="UTF-8" standalone="yes"?>
<networkModel>
    <cablesMap>
        <entry>
            <key>4</key>
            <value idAsString="4">
                <component1>0</component1>
                <component2>2</component2>
                <delay>10</delay>
                <hwType>CABLE_ETHERNET</hwType>
                <id>4</id>
                <interface1>1</interface1>
                <interface2>3</interface2>
            </value>
        </entry>
    </cablesMap>
    <componentsMap>
        <entry>
            <key>0</key>
            <value idAsString="0">
                <defaultZoomXPos>126</defaultZoomXPos>
                <defaultZoomYPos>168</defaultZoomYPos>
                <devSettings>
                    <natConfig/>
                    <netModType>tcp_ip_netmod</netModType>
                    <routingTabConfig>
                        <routingTableItem>
                            <destination>147.32.116.0/24</destination>
                            <interfaceName>eth0</interfaceName>
                        </routingTableItem>
                        <routingTableItem>
                            <destination>0.0.0.0/0</destination>
                            <gateway>147.32.116.1</gateway>
                            <interfaceName>eth0</interfaceName>
                        </routingTableItem>
                    </routingTabConfig>
                </devSettings>
                <hwType>END_DEVICE_PC</hwType>
                <id>0</id>
                <interface hwComponent="0" idAsString="1">
                    <cable>4</cable>
                    <hwType>END_DEVICE_PC</hwType>
                    <id>1</id>
                    <ipAddress>147.32.116.207/24</ipAddress>
                    <isUp>true</isUp>
                    <macAddress>60-EB-69-2C-7E-94</macAddress>
                    <name>eth0</name>
                </interface>
                <name>pc0</name>
            </value>
        </entry>
        <entry>
            <key>2</key>
            <value idAsString="2">
                <defaultZoomXPos>643</defaultZoomXPos>
                <defaultZoomYPos>370</defaultZoomYPos>
                <hwType>REAL_PC</hwType>
                <id>2</id>
                <interface hwComponent="2" idAsString="3">
                    <cable>4</cable>
                    <hwType>REAL_PC</hwType>
                    <id>3</id>
                    <ipAddress></ipAddress>
                    <isUp>false</isUp>
                    <macAddress></macAddress>
                    <name>eth0</name>
                </interface>
                <name>realpc0</name>
            </value>
        </entry>
    </componentsMap>
    <id>-1</id>
    <lastEditTimestamp>1400113301117</lastEditTimestamp>
    <counter>
        <nextId>6</nextId>
        <nextMacAddress>0</nextMacAddress>
        <nextNumberMap>
            <entry>
                <key>END_DEVICE_PC</key>
                <value>1</value>
            </entry>
            <entry>
                <key>BUNDLE_OF_CABLES</key>
                <value>0</value>
            </entry>
            <entry>
                <key>CABLE_ETHERNET</key>
                <value>0</value>
            </entry>
            <entry>
                <key>END_DEVICE_WORKSTATION</key>
                <value>0</value>
            </entry>
            <entry>
                <key>CISCO_SWITCH</key>
                <value>0</value>
            </entry>
            <entry>
                <key>END_DEVICE_NOTEBOOK</key>
                <value>0</value>
            </entry>
            <entry>
                <key>REAL_PC</key>
                <value>1</value>
            </entry>
            <entry>
                <key>CISCO_ROUTER</key>
                <value>0</value>
            </entry>
            <entry>
                <key>LINUX_SWITCH</key>
                <value>0</value>
            </entry>
            <entry>
                <key>CABLE_OPTIC</key>
                <value>0</value>
            </entry>
            <entry>
                <key>LINUX_ROUTER</key>
                <value>0</value>
            </entry>
        </nextNumberMap>
    </counter>
</networkModel>
